{"contract":"0x26e6c899b5a5dc1d4874d828fda515a7eb7baf00","contract_eth_balance":"5.032248488839178197","total_eth":4.99795403,"addresses_with_balance":111,"coverage_pct":99.32,"scan_date":"2026-04-02 17:00:39 UTC","distribution":{"1-10 ETH":{"count":1,"total_eth":1.0933727204529209},"0.1-1 ETH":{"count":10,"total_eth":3.4397239501030565},"0.01-0.1 ETH":{"count":10,"total_eth":0.43716490582235307},"<0.01 ETH":{"count":90,"total_eth":0.027692453999504256}},"activity":[{"month":"2020-07","tx_count":766},{"month":"2020-08","tx_count":24},{"month":"2020-09","tx_count":4},{"month":"2020-10","tx_count":9},{"month":"2020-11","tx_count":3},{"month":"2020-12","tx_count":5},{"month":"2021-01","tx_count":2},{"month":"2021-02","tx_count":4},{"month":"2021-04","tx_count":2},{"month":"2021-05","tx_count":8},{"month":"2021-06","tx_count":16},{"month":"2021-07","tx_count":13},{"month":"2021-08","tx_count":3},{"month":"2021-09","tx_count":2},{"month":"2021-10","tx_count":6},{"month":"2021-11","tx_count":3},{"month":"2021-12","tx_count":2},{"month":"2022-04","tx_count":3},{"month":"2022-08","tx_count":4},{"month":"2022-09","tx_count":2},{"month":"2024-07","tx_count":1},{"month":"2024-10","tx_count":1},{"month":"2025-02","tx_count":1},{"month":"2025-03","tx_count":7},{"month":"2025-05","tx_count":1}],"tvl":[{"month":"2020-08","eth":58.5295},{"month":"2020-09","eth":57.5953},{"month":"2020-10","eth":56.8151},{"month":"2020-11","eth":56.4389},{"month":"2020-12","eth":56.4385},{"month":"2021-01","eth":55.1377},{"month":"2021-02","eth":54.9495},{"month":"2021-03","eth":53.9585},{"month":"2021-04","eth":53.9585},{"month":"2021-05","eth":53.5673},{"month":"2021-06","eth":45.6701},{"month":"2021-07","eth":36.8253},{"month":"2021-08","eth":29.5071},{"month":"2021-09","eth":23.7662},{"month":"2021-10","eth":19.9467},{"month":"2021-11","eth":15.183},{"month":"2021-12","eth":12.7544},{"month":"2022-01","eth":12.6677},{"month":"2022-02","eth":12.6677},{"month":"2022-03","eth":12.6677},{"month":"2022-04","eth":12.6677},{"month":"2022-05","eth":12.564},{"month":"2022-06","eth":12.564},{"month":"2022-07","eth":12.564},{"month":"2022-08","eth":12.564},{"month":"2022-09","eth":12.4674},{"month":"2022-10","eth":12.4263},{"month":"2022-11","eth":12.4263},{"month":"2022-12","eth":12.4263},{"month":"2023-01","eth":12.4263},{"month":"2023-02","eth":12.4263},{"month":"2023-03","eth":12.4263},{"month":"2023-04","eth":12.4263},{"month":"2023-05","eth":12.4263},{"month":"2023-06","eth":12.4263},{"month":"2023-07","eth":12.4263},{"month":"2023-08","eth":12.4263},{"month":"2023-09","eth":12.4263},{"month":"2023-10","eth":12.4263},{"month":"2023-11","eth":12.4263},{"month":"2023-12","eth":12.4263},{"month":"2024-01","eth":12.4263},{"month":"2024-02","eth":12.4263},{"month":"2024-03","eth":12.4263},{"month":"2024-04","eth":12.4263},{"month":"2024-05","eth":12.4263},{"month":"2024-06","eth":12.4263},{"month":"2024-07","eth":12.4263},{"month":"2024-08","eth":12.4044},{"month":"2024-09","eth":12.4044},{"month":"2024-10","eth":12.4044},{"month":"2024-11","eth":12.4044},{"month":"2024-12","eth":12.4044},{"month":"2025-01","eth":12.4044},{"month":"2025-02","eth":12.4044},{"month":"2025-03","eth":12.4043},{"month":"2025-04","eth":12.4043},{"month":"2025-05","eth":12.4043},{"month":"2025-06","eth":12.394},{"month":"2025-07","eth":12.394},{"month":"2025-08","eth":12.394},{"month":"2025-09","eth":12.394},{"month":"2025-10","eth":12.394},{"month":"2025-11","eth":12.394},{"month":"2025-12","eth":12.394},{"month":"2026-01","eth":12.394},{"month":"2026-02","eth":12.394},{"month":"2026-03","eth":12.394}]}