{
  "contract": "0x943e99d9efd4b44d808f6c83373a9a2c1e15e0f8",
  "balance_source": "eth",
  "name": "ForegroundTokenSale (DEAL)",
  "description": "Direct-refund ICO crowdsale \u2014 ForegroundTokenSale (DEAL). ETH stored in the crowdsale itself, not a vault.",
  "scan_date": "2026-04-07 15:23:01 UTC",
  "contract_eth_balance": "12.145",
  "total_addresses_scanned": 54,
  "addresses_with_balance": 18,
  "total_eth_in_balances": 12.145,
  "coverage_pct": 100.0,
  "distribution": {
    "1-10 ETH": {
      "count": 2,
      "total_eth": 5.98
    },
    "0.1-1 ETH": {
      "count": 12,
      "total_eth": 5.920000000000001
    },
    "0.01-0.1 ETH": {
      "count": 4,
      "total_eth": 0.245
    }
  },
  "balances": [
    {
      "rank": 1,
      "address": "0x7af49f444a59c39722fffbfd3d26f7825db42f42",
      "balance_wei": "4980000000000000000",
      "balance_eth": "4.980000000000000426"
    },
    {
      "rank": 2,
      "address": "0x3b74f3a115c9c4b76f4a4e321df2dcdb195d153d",
      "balance_wei": "1000000000000000000",
      "balance_eth": "1.000000000000000000"
    },
    {
      "rank": 3,
      "address": "0xa0cac7e600bb2f59027dc8ccbf1387d8112c46eb",
      "balance_wei": "980000000000000000",
      "balance_eth": "0.979999999999999982"
    },
    {
      "rank": 4,
      "address": "0xaed228af7ec3e3896be29c739a9bab65bb02149a",
      "balance_wei": "975000000000000000",
      "balance_eth": "0.974999999999999978"
    },
    {
      "rank": 5,
      "address": "0xc396c795da2306d6c46ccc016aba7d9df58bdf58",
      "balance_wei": "960000000000000000",
      "balance_eth": "0.959999999999999964"
    },
    {
      "rank": 6,
      "address": "0xe94992e1fed652887b415f8b4606a195d3cc6469",
      "balance_wei": "950000000000000000",
      "balance_eth": "0.949999999999999956"
    },
    {
      "rank": 7,
      "address": "0x00fad5eec97a131ba5523fc2558248028a31611b",
      "balance_wei": "560000000000000000",
      "balance_eth": "0.560000000000000053"
    },
    {
      "rank": 8,
      "address": "0x7ed1e469fcb3ee19c0366d829e291451be638e59",
      "balance_wei": "350000000000000000",
      "balance_eth": "0.349999999999999978"
    },
    {
      "rank": 9,
      "address": "0xf8d868bfab71131f7dc0c6efca93b6e639626af6",
      "balance_wei": "300000000000000000",
      "balance_eth": "0.299999999999999989"
    },
    {
      "rank": 10,
      "address": "0x23dae45c3a379637914dfd6df269c46c6a0fbeed",
      "balance_wei": "280000000000000000",
      "balance_eth": "0.280000000000000027"
    },
    {
      "rank": 11,
      "address": "0x6809a2e9f371b79e962d86362c0dfe9c3bf82635",
      "balance_wei": "195000000000000000",
      "balance_eth": "0.195000000000000007"
    },
    {
      "rank": 12,
      "address": "0xc5541387416cc204800277055497d70c1d547fef",
      "balance_wei": "150000000000000000",
      "balance_eth": "0.149999999999999994"
    },
    {
      "rank": 13,
      "address": "0xeb9cc77a1c9742f7b63520d61e5b1da3db099f92",
      "balance_wei": "120000000000000000",
      "balance_eth": "0.119999999999999996"
    },
    {
      "rank": 14,
      "address": "0x75e7f640bf6968b6f32c47a3cd82c3c2c9dcae68",
      "balance_wei": "100000000000000000",
      "balance_eth": "0.100000000000000006"
    },
    {
      "rank": 15,
      "address": "0xd682167f53f7bb1e243d3e3e054b9400a608a48e",
      "balance_wei": "80000000000000000",
      "balance_eth": "0.080000000000000002"
    },
    {
      "rank": 16,
      "address": "0xdef17d78cc06c93d2eb516843365c965bb41fb45",
      "balance_wei": "65000000000000000",
      "balance_eth": "0.065000000000000002"
    },
    {
      "rank": 17,
      "address": "0x636eb42c4f8fc8b9d37316ac586943c29f9bdf62",
      "balance_wei": "50000000000000000",
      "balance_eth": "0.050000000000000003"
    },
    {
      "rank": 18,
      "address": "0xa54b8c69a8fed06bd0c0cc980c3ef64cf2528b15",
      "balance_wei": "50000000000000000",
      "balance_eth": "0.050000000000000003"
    }
  ]
}